bsp_tool/__init__.py
bsp_tool/autodetect.py
bsp_tool/base.py
bsp_tool/bspx.py
bsp_tool/external.py
bsp_tool/id_software.py
bsp_tool/infinity_ward.py
bsp_tool/lumps.py
bsp_tool/nexon.py
bsp_tool/raven.py
bsp_tool/respawn.py
bsp_tool/ritual.py
bsp_tool/valve.py
bsp_tool/wild_tangent.py
bsp_tool/archives/__init__.py
bsp_tool/archives/alcohol.py
bsp_tool/archives/base.py
bsp_tool/archives/bluepoint.py
bsp_tool/archives/cdrom.py
bsp_tool/archives/gearbox.py
bsp_tool/archives/golden_hawk.py
bsp_tool/archives/id_software.py
bsp_tool/archives/infinity_ward.py
bsp_tool/archives/ion_storm.py
bsp_tool/archives/mame.py
bsp_tool/archives/nexon.py
bsp_tool/archives/padus.py
bsp_tool/archives/pi_studios.py
bsp_tool/archives/pkware.py
bsp_tool/archives/ritual.py
bsp_tool/archives/sega.py
bsp_tool/archives/troika.py
bsp_tool/archives/utoplanet.py
bsp_tool/archives/valve.py
bsp_tool/archives/respawn/__init__.py
bsp_tool/archives/respawn/rpak.py
bsp_tool/branches/__init__.py
bsp_tool/branches/bspx.py
bsp_tool/branches/colour.py
bsp_tool/branches/ieee754.py
bsp_tool/branches/shared.py
bsp_tool/branches/time.py
bsp_tool/branches/ace_team/__init__.py
bsp_tool/branches/ace_team/zeno_clash.py
bsp_tool/branches/arkane/__init__.py
bsp_tool/branches/arkane/dark_messiah_mp.py
bsp_tool/branches/arkane/dark_messiah_sp.py
bsp_tool/branches/gearbox/__init__.py
bsp_tool/branches/gearbox/blue_shift.py
bsp_tool/branches/gearbox/nightfire.py
bsp_tool/branches/id_software/__init__.py
bsp_tool/branches/id_software/qbism.py
bsp_tool/branches/id_software/qfusion.py
bsp_tool/branches/id_software/quake.py
bsp_tool/branches/id_software/quake2.py
bsp_tool/branches/id_software/quake3.py
bsp_tool/branches/id_software/quake64.py
bsp_tool/branches/id_software/remake_quake.py
bsp_tool/branches/id_software/remake_quake_old.py
bsp_tool/branches/infinity_ward/__init__.py
bsp_tool/branches/infinity_ward/call_of_duty1.py
bsp_tool/branches/infinity_ward/call_of_duty1_demo.py
bsp_tool-0.6.0.dist-info/METADATA
bsp_tool-0.6.0.dist-info/WHEEL
bsp_tool-0.6.0.dist-info/licenses/LICENSE.txt
bsp_tool-0.6.0.dist-info/RECORD
