Metadata-Version: 2.4
Name: bsp_tool
Version: 0.6.0
Summary: Python library for analysing .bsp files
Project-URL: Homepage, https://snake-biscuits.github.io/bsp_tool/
Project-URL: Repository, https://github.com/snake-biscuits/bsp_tool
Project-URL: Documentation, https://github.com/snake-biscuits/bsp_tool_docs
Project-URL: Changelog, https://github.com/snake-biscuits/bsp_tool/blob/master/CHANGELOG.md
Project-URL: Bug Reports, https://github.com/snake-biscuits/bsp_tool/issues
Project-URL: Funding, https://ko-fi.com/bikkie
Author: BobTheBob, rexx
Author-email: snake-biscuits <haveanotherbiscuit@gmail.com>
Maintainer-email: snake-biscuits <haveanotherbiscuit@gmail.com>
License:                     GNU GENERAL PUBLIC LICENSE
License-File: LICENSE.txt
Keywords: bsp,cod,idtech,quake,source,titanfall
Classifier: Development Status :: 4 - Beta
Classifier: Intended Audience :: Developers
Classifier: License :: OSI Approved :: GNU General Public License v3 (GPLv3)
Classifier: Operating System :: OS Independent
Classifier: Programming Language :: Python :: 3
Classifier: Programming Language :: Python :: 3 :: Only
Classifier: Programming Language :: Python :: 3.8
Classifier: Programming Language :: Python :: 3.9
Classifier: Programming Language :: Python :: 3.10
Classifier: Programming Language :: Python :: 3.11
Classifier: Programming Language :: Python :: 3.12
Classifier: Programming Language :: Python :: 3.13
Classifier: Topic :: Games/Entertainment :: First Person Shooters
Classifier: Topic :: Multimedia :: Graphics :: 3D Modeling
Classifier: Topic :: Software Development :: Libraries :: Python Modules
Requires-Python: >=3.8
Requires-Dist: pillow
Provides-Extra: test
Requires-Dist: pytest; extra == 'test'
Requires-Dist: pytest-cov; extra == 'test'
